{"id": 870274231900262401, "id_str": "870274231900262401", "name": "Stolen Picture", "screen_name": "StolenPictureUK", "location": "", "description": "Film & TV Production Company\nBrainchild of Simon Pegg and Nick Frost", "url": null, "entities": {"description": {"urls": []}}, "protected": false, "followers_count": 9999, "friends_count": 61, "listed_count": 22, "created_at": "Thu Jun 01 13:42:00 +0000 2017", "favourites_count": 13, "utc_offset": null, "time_zone": null, "geo_enabled": false, "verified": false, "statuses_count": 31, "lang": null, "status": {"created_at": "Mon Oct 19 10:08:30 +0000 2020", "id": 1318131905901023232, "id_str": "1318131905901023232", "text": "https://t.co/gOsvsmx8Dm", "truncated": false, "entities": {"hashtags": [], "symbols": [], "user_mentions": [], "urls": [], "media": [{"id": 1318131891615268869, "id_str": "1318131891615268869", "indices": [0, 23], "media_url": "http://pbs.twimg.com/media/Ekrx-L7XgAUVxda.jpg", "media_url_https": "https://pbs.twimg.com/media/Ekrx-L7XgAUVxda.jpg", "url": "https://t.co/gOsvsmx8Dm", "display_url": "pic.twitter.com/gOsvsmx8Dm", "expanded_url": "https://twitter.com/StolenPictureUK/status/1318131905901023232/photo/1", "type": "photo", "sizes": {"thumb": {"w": 150, "h": 150, "resize": "crop"}, "medium": {"w": 750, "h": 625, "resize": "fit"}, "small": {"w": 680, "h": 567, "resize": "fit"}, "large": {"w": 750, "h": 625, "resize": "fit"}}}]}, "extended_entities": {"media": [{"id": 1318131891615268869, "id_str": "1318131891615268869", "indices": [0, 23], "media_url": "http://pbs.twimg.com/media/Ekrx-L7XgAUVxda.jpg", "media_url_https": "https://pbs.twimg.com/media/Ekrx-L7XgAUVxda.jpg", "url": "https://t.co/gOsvsmx8Dm", "display_url": "pic.twitter.com/gOsvsmx8Dm", "expanded_url": "https://twitter.com/StolenPictureUK/status/1318131905901023232/photo/1", "type": "photo", "sizes": {"thumb": {"w": 150, "h": 150, "resize": "crop"}, "medium": {"w": 750, "h": 625, "resize": "fit"}, "small": {"w": 680, "h": 567, "resize": "fit"}, "large": {"w": 750, "h": 625, "resize": "fit"}}}, {"id": 1318131891590123520, "id_str": "1318131891590123520", "indices": [0, 23], "media_url": "http://pbs.twimg.com/media/Ekrx-L1X0AA23mk.jpg", "media_url_https": "https://pbs.twimg.com/media/Ekrx-L1X0AA23mk.jpg", "url": "https://t.co/gOsvsmx8Dm", "display_url": "pic.twitter.com/gOsvsmx8Dm", "expanded_url": "https://twitter.com/StolenPictureUK/status/1318131905901023232/photo/1", "type": "photo", "sizes": {"thumb": {"w": 150, "h": 150, "resize": "crop"}, "small": {"w": 513, "h": 680, "resize": "fit"}, "medium": {"w": 905, "h": 1200, "resize": "fit"}, "large": {"w": 1544, "h": 2048, "resize": "fit"}}}]}, "source": "<a href=\"http://twitter.com/download/iphone\" rel=\"nofollow\">Twitter for iPhone</a>", "in_reply_to_status_id": null, "in_reply_to_status_id_str": null, "in_reply_to_user_id": null, "in_reply_to_user_id_str": null, "in_reply_to_screen_name": null, "geo": null, "coordinates": null, "place": null, "contributors": null, "is_quote_status": false, "retweet_count": 14, "favorite_count": 65, "favorited": false, "retweeted": false, "possibly_sensitive": false, "lang": "und"}, "contributors_enabled": false, "is_translator": false, "is_translation_enabled": false, "profile_background_color": "F5F8FA", "profile_background_image_url": null, "profile_background_image_url_https": null, "profile_background_tile": false, "profile_image_url": "http://pbs.twimg.com/profile_images/1154699644846452737/OqxJSbQP_normal.jpg", "profile_image_url_https": "https://pbs.twimg.com/profile_images/1154699644846452737/OqxJSbQP_normal.jpg", "profile_banner_url": "https://pbs.twimg.com/profile_banners/870274231900262401/1602171616", "profile_link_color": "1DA1F2", "profile_sidebar_border_color": "C0DEED", "profile_sidebar_fill_color": "DDEEF6", "profile_text_color": "333333", "profile_use_background_image": true, "has_extended_profile": false, "default_profile": true, "default_profile_image": false, "following": false, "follow_request_sent": false, "notifications": false, "translator_type": "none"}
